profilis/__init__.py
profilis/py.typed
profilis/core/async_collector.py
profilis/core/emitter.py
profilis/core/stats.py
profilis/decorators/profile.py
profilis/exporters/console.py
profilis/exporters/jsonl.py
profilis/flask/adapter.py
profilis/flask/ui.py
profilis/mongo/instrumentation.py
profilis/neo4j/instrumentation.py
profilis/pyodbc/instrumentation.py
profilis/runtime/__init__.py
profilis/runtime/clock.py
profilis/runtime/context.py
profilis/runtime/ids.py
profilis/sqlalchemy/instrumentation.py
profilis-0.2.0.dist-info/licenses/LICENSE
profilis-0.2.0.dist-info/METADATA
profilis-0.2.0.dist-info/WHEEL
profilis-0.2.0.dist-info/top_level.txt
profilis-0.2.0.dist-info/RECORD
