Metadata-Version: 2.4
Name: profilis
Version: 0.2.0
Summary: High performance, non blocking profiler for Python web apps.
Author: Ankan Dutta
License-Expression: MIT
Project-URL: Homepage, https://github.com/ankan97dutta/profilis
Project-URL: Documentation, https://ankan97dutta.github.io/profilis/
Project-URL: Bug Tracker, https://github.com/ankan97dutta/profilis/issues
Keywords: profiler,python,flask,fastapi,sanic,sql,sqlalchemy,pyodbc,mongo,neo4j,asyncio,monitoring,performance
Classifier: Development Status :: 4 - Beta
Classifier: Intended Audience :: Developers
Classifier: Topic :: Software Development :: Libraries :: Python Modules
Classifier: Topic :: Software Development :: Testing
Classifier: Topic :: System :: Monitoring
Classifier: Programming Language :: Python :: 3
Classifier: Programming Language :: Python :: 3.9
Classifier: Programming Language :: Python :: 3.10
Classifier: Programming Language :: Python :: 3.11
Classifier: Programming Language :: Python :: 3.12
Classifier: Programming Language :: Python :: 3.13
Classifier: Operating System :: OS Independent
Requires-Python: >=3.9
License-File: LICENSE
Requires-Dist: typing_extensions>=4.0
Provides-Extra: flask
Requires-Dist: flask[async]>=3.0; extra == "flask"
Provides-Extra: fastapi
Requires-Dist: fastapi>=0.110; extra == "fastapi"
Requires-Dist: starlette>=0.37; extra == "fastapi"
Provides-Extra: sanic
Requires-Dist: sanic>=23.0; extra == "sanic"
Provides-Extra: sqlalchemy
Requires-Dist: sqlalchemy>=2.0; extra == "sqlalchemy"
Requires-Dist: aiosqlite; extra == "sqlalchemy"
Requires-Dist: greenlet; extra == "sqlalchemy"
Provides-Extra: pyodbc
Requires-Dist: pyodbc; extra == "pyodbc"
Provides-Extra: mongo
Requires-Dist: pymongo>=4.3; extra == "mongo"
Requires-Dist: motor>=3.3; extra == "mongo"
Provides-Extra: neo4j
Requires-Dist: neo4j>=5.14; extra == "neo4j"
Provides-Extra: perf
Requires-Dist: orjson>=3.8; extra == "perf"
Provides-Extra: all
Requires-Dist: flask[async]>=3.0; extra == "all"
Requires-Dist: fastapi>=0.110; extra == "all"
Requires-Dist: starlette>=0.37; extra == "all"
Requires-Dist: sanic>=23.0; extra == "all"
Requires-Dist: sqlalchemy>=2.0; extra == "all"
Requires-Dist: aiosqlite; extra == "all"
Requires-Dist: greenlet; extra == "all"
Requires-Dist: pyodbc; extra == "all"
Requires-Dist: pymongo>=4.3; extra == "all"
Requires-Dist: motor>=3.3; extra == "all"
Requires-Dist: neo4j>=5.14; extra == "all"
Requires-Dist: orjson>=3.8; extra == "all"
Provides-Extra: dev
Requires-Dist: pytest>=7.0; extra == "dev"
Requires-Dist: pytest-cov>=4.0; extra == "dev"
Requires-Dist: pytest-asyncio>=0.21.0; extra == "dev"
Requires-Dist: mypy>=1.0; extra == "dev"
Requires-Dist: ruff>=0.1.0; extra == "dev"
Requires-Dist: black>=23.0; extra == "dev"
Requires-Dist: pre-commit>=3.0; extra == "dev"
Dynamic: license-file
